google/cloud/iap/__init__.py
google/cloud/iap/gapic_version.py
google/cloud/iap/py.typed
google/cloud/iap_v1/__init__.py
google/cloud/iap_v1/gapic_metadata.json
google/cloud/iap_v1/gapic_version.py
google/cloud/iap_v1/py.typed
google/cloud/iap_v1/services/__init__.py
google/cloud/iap_v1/services/identity_aware_proxy_admin_service/__init__.py
google/cloud/iap_v1/services/identity_aware_proxy_admin_service/async_client.py
google/cloud/iap_v1/services/identity_aware_proxy_admin_service/client.py
google/cloud/iap_v1/services/identity_aware_proxy_admin_service/pagers.py
google/cloud/iap_v1/services/identity_aware_proxy_admin_service/transports/__init__.py
google/cloud/iap_v1/services/identity_aware_proxy_admin_service/transports/base.py
google/cloud/iap_v1/services/identity_aware_proxy_admin_service/transports/grpc.py
google/cloud/iap_v1/services/identity_aware_proxy_admin_service/transports/grpc_asyncio.py
google/cloud/iap_v1/services/identity_aware_proxy_admin_service/transports/rest.py
google/cloud/iap_v1/services/identity_aware_proxy_admin_service/transports/rest_base.py
google/cloud/iap_v1/services/identity_aware_proxy_o_auth_service/__init__.py
google/cloud/iap_v1/services/identity_aware_proxy_o_auth_service/async_client.py
google/cloud/iap_v1/services/identity_aware_proxy_o_auth_service/client.py
google/cloud/iap_v1/services/identity_aware_proxy_o_auth_service/pagers.py
google/cloud/iap_v1/services/identity_aware_proxy_o_auth_service/transports/__init__.py
google/cloud/iap_v1/services/identity_aware_proxy_o_auth_service/transports/base.py
google/cloud/iap_v1/services/identity_aware_proxy_o_auth_service/transports/grpc.py
google/cloud/iap_v1/services/identity_aware_proxy_o_auth_service/transports/grpc_asyncio.py
google/cloud/iap_v1/services/identity_aware_proxy_o_auth_service/transports/rest.py
google/cloud/iap_v1/services/identity_aware_proxy_o_auth_service/transports/rest_base.py
google/cloud/iap_v1/types/__init__.py
google/cloud/iap_v1/types/service.py
google_cloud_iap-1.18.0.dist-info/licenses/LICENSE
google_cloud_iap-1.18.0.dist-info/METADATA
google_cloud_iap-1.18.0.dist-info/WHEEL
google_cloud_iap-1.18.0.dist-info/top_level.txt
google_cloud_iap-1.18.0.dist-info/RECORD
